ArrayExpressions/__init__.py
ArrayExpressions/arrex.py
arrayexpressions-0.0.3.dist-info/METADATA
arrayexpressions-0.0.3.dist-info/WHEEL
arrayexpressions-0.0.3.dist-info/licenses/LICENSE
arrayexpressions-0.0.3.dist-info/RECORD
