Metadata-Version: 2.4
Name: ArrayExpressions
Version: 0.0.3
Summary: Array Expressions - Shorthand Language for Array Manipulation
Project-URL: Homepage, https://github.com/danielpagano202/ArrEx
Project-URL: Issues, https://github.com/danielpagano202/ArrEx/issues
Author-email: Daniel Pagano <danielpagano202@gmail.com>
License-File: LICENSE
Classifier: License :: OSI Approved :: MIT License
Classifier: Operating System :: OS Independent
Classifier: Programming Language :: Python :: 3
Requires-Python: >=3.8
